replica_generator/__init__.py
replica_generator/replica_generator.py
replica_generator-0.1.0.dist-info/LICENSE
replica_generator-0.1.0.dist-info/METADATA
replica_generator-0.1.0.dist-info/WHEEL
replica_generator-0.1.0.dist-info/top_level.txt
replica_generator-0.1.0.dist-info/RECORD
