Metadata-Version: 2.1
Name: replica-generator
Version: 0.1.0
Summary: A library to generate replica images using Hugging Face models.
Home-page: https://github.com/kushcoder12/Replica-Generator
Author: Kushagra Vyas
Author-email: vyaskushagra2003@gmail.com
Classifier: Programming Language :: Python :: 3
Classifier: License :: OSI Approved :: MIT License
Classifier: Operating System :: OS Independent
Requires-Python: >=3.6
License-File: LICENSE
Requires-Dist: torch
Requires-Dist: transformers
Requires-Dist: diffusers
